eda_assistant/__init__.py
eda_assistant/_calc_dataframe_statistics.py
eda_assistant/_calc_variable_statistics.py
eda_assistant/_create_graphs.py
eda_assistant/_create_tables.py
eda_assistant/_format_eda_report.py
eda_assistant/_format_graphs.py
eda_assistant/_format_tables.py
eda_assistant/eda_assistant.py
eda_assistant/tests/__init__.py
eda_assistant/tests/test_calc_dataframe_statistics.py
eda_assistant/tests/test_calc_variable_statistics.py
eda_assistant/tests/test_create_tables.py
eda_assistant/tests/test_eda_assistant.py
eda_assistant/tests/test_format_graphs.py
eda_assistant/tests/test_format_tables.py
EDA_assistant-0.0.4.dist-info/LICENSE
EDA_assistant-0.0.4.dist-info/METADATA
EDA_assistant-0.0.4.dist-info/WHEEL
EDA_assistant-0.0.4.dist-info/top_level.txt
EDA_assistant-0.0.4.dist-info/RECORD
