Metadata-Version: 2.1
Name: EDA-assistant
Version: 0.0.4
Summary: This package allows users to perform exploratory data analysis tasks and techniques such as creating an EDA PDF report from any dataset
Home-page: https://github.com/madalynli/EDA-assistant
Author: Madalyn Li
Author-email: mli2324@uw.edu
License: UNKNOWN
Platform: UNKNOWN
Classifier: Programming Language :: Python :: 3
Classifier: License :: OSI Approved :: MIT License
Classifier: Operating System :: OS Independent
License-File: LICENSE
Requires-Dist: cycler
Requires-Dist: fonttools
Requires-Dist: kiwisolver
Requires-Dist: matplotlib
Requires-Dist: numpy
Requires-Dist: packaging
Requires-Dist: pandas
Requires-Dist: Pillow
Requires-Dist: pyparsing
Requires-Dist: python-dateutil
Requires-Dist: pytz
Requires-Dist: scipy
Requires-Dist: seaborn
Requires-Dist: six
